osversionchecker/LICENSE.txt
osversionchecker/README.MD
osversionchecker/__init__.py
osversionchecker/requirements.txt
osversionchecker/thirdparty.json
osversionchecker-0.10.dist-info/LICENSE.rst
osversionchecker-0.10.dist-info/METADATA
osversionchecker-0.10.dist-info/WHEEL
osversionchecker-0.10.dist-info/top_level.txt
osversionchecker-0.10.dist-info/RECORD
